alibabacloud_ahas_openapi20190901/__init__.py
alibabacloud_ahas_openapi20190901/client.py
alibabacloud_ahas_openapi20190901/models.py
alibabacloud_ahas_openapi20190901-1.0.2.dist-info/LICENSE
alibabacloud_ahas_openapi20190901-1.0.2.dist-info/METADATA
alibabacloud_ahas_openapi20190901-1.0.2.dist-info/WHEEL
alibabacloud_ahas_openapi20190901-1.0.2.dist-info/top_level.txt
alibabacloud_ahas_openapi20190901-1.0.2.dist-info/RECORD
