Metadata-Version: 2.1
Name: alibabacloud-ahas-openapi20190901
Version: 1.0.2
Summary: Alibaba Cloud ahas-openapi (20190901) SDK Library for Python
Home-page: https://github.com/aliyun/alibabacloud-python-sdk
Author: Alibaba Cloud SDK
Author-email: sdk-team@alibabacloud.com
License: Apache License 2.0
Keywords: alibabacloud,ahas,openapi20190901
Platform: any
Classifier: Development Status :: 4 - Beta
Classifier: Intended Audience :: Developers
Classifier: License :: OSI Approved :: Apache Software License
Classifier: Programming Language :: Python
Classifier: Programming Language :: Python :: 3
Classifier: Programming Language :: Python :: 3.6
Classifier: Programming Language :: Python :: 3.7
Classifier: Programming Language :: Python :: 3.8
Classifier: Programming Language :: Python :: 3.9
Classifier: Topic :: Software Development
Requires-Python: >=3.6
Requires-Dist: alibabacloud-tea-util (<1.0.0,>=0.3.3)
Requires-Dist: alibabacloud-tea-openapi (<1.0.0,>=0.2.4)
Requires-Dist: alibabacloud-endpoint-util (<1.0.0,>=0.0.3)
